[
    {
        "email": "heidi@gmail.com",
        "password": "$2a$10$32ksKV6KWfIdfbpK4PKPLOiiXP4CDrM5BrHhwcfAXjRQRomUdG0Gy",
        "balance": 10000,
        "currencies": [
            {
                "currency": "UniCoin",
                "amount": 57,
                "value": 1197
            },
            {
                "currency": "BaCoin",
                "amount": 3,
                "value": 15
            },
            {
                "currency": "IceCreamCoin",
                "amount": 12,
                "value": 155
            }
        ]
    }
]
